easy_exchange_rates/__init__.py
easy_exchange_rates/eer.py
easy_exchange_rates-0.2.0.dist-info/LICENSE
easy_exchange_rates-0.2.0.dist-info/METADATA
easy_exchange_rates-0.2.0.dist-info/WHEEL
easy_exchange_rates-0.2.0.dist-info/top_level.txt
easy_exchange_rates-0.2.0.dist-info/RECORD
