Metadata-Version: 2.1
Name: easy_exchange_rates
Version: 0.2.0
Summary: Easy way to get currency exchange data from https://data.ecb.europa.eu/ to a pandas dataframe.
Home-page: https://github.com/oddaspa/easy-exchange-rates
Author: Odd Gunnar Aspaas
Author-email: odd.gunnar.aspaas@gmail.com
Project-URL: Bug Tracker, https://github.com/oddaspa/easy-exchange-rates/issues
Classifier: Programming Language :: Python :: 3
Classifier: License :: OSI Approved :: MIT License
Classifier: Operating System :: OS Independent
Requires-Python: >=3.8
License-File: LICENSE
